{
    "data":[
      {
        "tag": "5_E_0023",
        "id": "41414141",
        "sifon": "4.0",
       "pisuvar": "4.0",
        "sabunluk": "5.0",
        "peçetelik": "4.0",
        "rulo": "4.0"
      },
      {
        "tag": "5_E_0019",
        "id": "41414142",
        "sifon": "8.0",
       "pisuvar": "0.0",
        "sabunluk": "1.0",
        "peçetelik": "6.0",
        "rulo": "8.0"
      },
      {
        "tag": "5_E_0066",
        "id": "41414143",
        "sifon": "4.0",
       "pisuvar": "4.0",
        "sabunluk": "8.0",
        "peçetelik": "4.0",
        "rulo": "4.0"
      },
      {
        "tag": "5_E_0069",
        "id": "41414144",
        "sifon": "4.0",
       "pisuvar": "0.0",
        "sabunluk": "1.0",
        "peçetelik": "3.0",
        "rulo": "4.0"
      },
      {
        "tag": "5_E_0071",
        "id": "41414145",
        "sifon": "1.0",
       "pisuvar": "0.0",
        "sabunluk": "1.0",
        "peçetelik": "1.0",
        "rulo": "1.0"
      },
      {
        "tag": "5_E_0073",
        "id": "41414146",
        "sifon": "1.0",
       "pisuvar": "1.0",
        "sabunluk": "1.0",
        "peçetelik": "1.0",
        "rulo": "1.0"
      },
      {
        "tag": "5_E_0095",
        "id": "41414241",
        "sifon": "1.0",
       "pisuvar": "0.0",
        "sabunluk": "1.0",
        "peçetelik": "1.0",
        "rulo": "1.0"
      },
      {
        "tag": "5_E_0097",
        "id": "41414242",
        "sifon": "1.0",
       "pisuvar": "1.0",
        "sabunluk": "1.0",
        "peçetelik": "1.0",
        "rulo": "1.0"
      },
      {
        "tag": "5_E_0113",
        "id": "41414243",
        "sifon": "1.0",
       "pisuvar": "0.0",
        "sabunluk": "1.0",
        "peçetelik": "1.0",
        "rulo": "1.0"
      },
      {
        "tag": "5_E_0115",
        "id": "41414244",
        "sifon": "1.0",
       "pisuvar": "1.0",
        "sabunluk": "1.0",
        "peçetelik": "1.0",
        "rulo": "1.0"
      },
      {
        "tag": "5_E_0127",
        "id": "41414245",
        "sifon": "8.0",
       "pisuvar": "0.0",
        "sabunluk": "8.0",
        "peçetelik": "6.0",
        "rulo": "8.0"
      },
      {
        "tag": "5_E_0131",
        "id": "41414246",
        "sifon": "4.0",
       "pisuvar": "4.0",
        "sabunluk": "5.0",
        "peçetelik": "4.0",
        "rulo": "4.0"
      },
      {
        "tag": "5_E_0141",
        "id": "41414341",
        "sifon": "1.0",
       "pisuvar": "0.0",
        "sabunluk": "1.0",
        "peçetelik": "1.0",
        "rulo": "1.0"
      },
      {
        "tag": "5_E_0143",
        "id": "41414342",
        "sifon": "1.0",
       "pisuvar": "1.0",
        "sabunluk": "1.0",
        "peçetelik": "1.0",
        "rulo": "1.0"
      },
      {
        "tag": "5_E_0163",
        "id": "41414344",
        "sifon": "5.0",
       "pisuvar": "5.0",
        "sabunluk": "5.0",
        "peçetelik": "4.0",
        "rulo": "5.0"
      },
      {
        "tag": "5_E_0166",
        "id": "41414345",
        "sifon": "5.0",
       "pisuvar": "0.0",
        "sabunluk": "5.0",
        "peçetelik": "4.0",
        "rulo": "5.0"
      },
      {
        "tag": "5_F_0060",
        "id": "41414346",
        "sifon": "4.0",
       "pisuvar": "0.0",
        "sabunluk": "4.0",
        "peçetelik": "3.0",
        "rulo": "4.0"
      },
      {
        "tag": "5_F_0061",
        "id": "41414441",
        "sifon": "3.0",
       "pisuvar": "3.0",
        "sabunluk": "4.0",
        "peçetelik": "3.0",
        "rulo": "3.0"
      },
      {
        "tag": "5_F_0044",
        "id": "41414442",
        "sifon": "4.0",
       "pisuvar": "0.0",
        "sabunluk": "4.0",
        "peçetelik": "3.0",
        "rulo": "4.0"
      },
      {
        "tag": "5_F_0045",
        "id": "41414443",
        "sifon": "3.0",
       "pisuvar": "3.0",
        "sabunluk": "4.0",
        "peçetelik": "3.0",
        "rulo": "3.0"
      },
      {
        "tag": "5_F_0028",
        "id": "41414444",
        "sifon": "4.0",
       "pisuvar": "0.0",
        "sabunluk": "4.0",
        "peçetelik": "3.0",
        "rulo": "4.0"
      },
      {
        "tag": "5_F_0029",
        "id": "41414445",
        "sifon": "3.0",
       "pisuvar": "3.0",
        "sabunluk": "4.0",
        "peçetelik": "3.0",
        "rulo": "3.0"
      },
      {
        "tag": "5_F_0012",
        "id": "41414446",
        "sifon": "4.0",
       "pisuvar": "0.0",
        "sabunluk": "4.0",
        "peçetelik": "3.0",
        "rulo": "4.0"
      },
      {
        "tag": "5_F_0013",
        "id": "41414541",
        "sifon": "3.0",
       "pisuvar": "3.0",
        "sabunluk": "4.0",
        "peçetelik": "3.0",
        "rulo": "3.0"
      },
      {
        "tag": "1_E_0036",
        "id": "41414542",
        "sifon": "8.0",
       "pisuvar": "0.0",
        "sabunluk": "8.0",
        "peçetelik": "6.0",
        "rulo": "8.0"
      },
      {
        "tag": "1_E_0032",
        "id": "41414543",
        "sifon": "4.0",
       "pisuvar": "4.0",
        "sabunluk": "5.0",
        "peçetelik": "4.0",
        "rulo": "4.0"
      },
      {
        "tag": "1_E_0170",
        "id": "41414544",
        "sifon": "1.0",
       "pisuvar": "0.0",
        "sabunluk": "1.0",
        "peçetelik": "1.0",
        "rulo": "1.0"
      },
      {
        "tag": "1_E_0168",
        "id": "41414545",
        "sifon": "1.0",
       "pisuvar": "1.0",
        "sabunluk": "1.0",
        "peçetelik": "1.0",
        "rulo": "1.0"
      },
      {
        "tag": "1_E_0051",
        "id": "41414546",
        "sifon": "5.0",
       "pisuvar": "0.0",
        "sabunluk": "5.0",
        "peçetelik": "4.0",
        "rulo": "5.0"
      },
      {
        "tag": "1_E_0047",
        "id": "41414641",
        "sifon": "5.0",
       "pisuvar": "5.0",
        "sabunluk": "5.0",
        "peçetelik": "4.0",
        "rulo": "5.0"
      },
      {
        "tag": "1_E_0075",
        "id": "41414642",
        "sifon": "5.0",
       "pisuvar": "0.0",
        "sabunluk": "5.0",
        "peçetelik": "4.0",
        "rulo": "5.0"
      },
      {
        "tag": "1_E_0079",
        "id": "41414643",
        "sifon": "5.0",
       "pisuvar": "5.0",
        "sabunluk": "5.0",
        "peçetelik": "4.0",
        "rulo": "5.0"
      },
      {
        "tag": "1_E_0085",
        "id": "41414644",
        "sifon": "1.0",
       "pisuvar": "0.0",
        "sabunluk": "1.0",
        "peçetelik": "1.0",
        "rulo": "1.0"
      },
      {
        "tag": "1_E_0087",
        "id": "41414645",
        "sifon": "1.0",
       "pisuvar": "1.0",
        "sabunluk": "1.0",
        "peçetelik": "1.0",
        "rulo": "1.0"
      },
      {
        "tag": "1_E_0118",
        "id": "41414646",
        "sifon": "4.0",
       "pisuvar": "0.0",
        "sabunluk": "4.0",
        "peçetelik": "3.0",
        "rulo": "4.0"
      },
      {
        "tag": "1_E_0119",
        "id": "41424141",
        "sifon": "4.0",
       "pisuvar": "4.0",
        "sabunluk": "4.0",
        "peçetelik": "3.0",
        "rulo": "4.0"
      },
      {
        "tag": "1_F_0078",
        "id": "41424142",
        "sifon": "4.0",
       "pisuvar": "0.0",
        "sabunluk": "4.0",
        "peçetelik": "3.0",
        "rulo": "4.0"
      },
      {
        "tag": "1_F_0074",
        "id": "41424143",
        "sifon": "4.0",
       "pisuvar": "4.0",
        "sabunluk": "4.0",
        "peçetelik": "3.0",
        "rulo": "4.0"
      },
      {
        "tag": "1_F_0054",
        "id": "41424144",
        "sifon": "4.0",
       "pisuvar": "0.0",
        "sabunluk": "3.0",
        "peçetelik": "2.0",
        "rulo": "4.0"
      },
      {
        "tag": "1_F_0053",
        "id": "41424145",
        "sifon": "3.0",
       "pisuvar": "3.0",
        "sabunluk": "3.0",
        "peçetelik": "2.0",
        "rulo": "3.0"
      },
      {
        "tag": "1_F_0042",
        "id": "41424146",
        "sifon": "2.0",
       "pisuvar": "2.0",
        "sabunluk": "3.0",
        "peçetelik": "2.0",
        "rulo": "2.0"
      },
      {
        "tag": "1_F_0045",
        "id": "41424241",
        "sifon": "3.0",
       "pisuvar": "0.0",
        "sabunluk": "3.0",
        "peçetelik": "2.0",
        "rulo": "3.0"
      },
      {
        "tag": "1_F_0027",
        "id": "41424242",
        "sifon": "3.0",
       "pisuvar": "0.0",
        "sabunluk": "3.0",
        "peçetelik": "2.0",
        "rulo": "3.0"
      },
      {
        "tag": "1_F_0024",
        "id": "41424243",
        "sifon": "2.0",
       "pisuvar": "2.0",
        "sabunluk": "3.0",
        "peçetelik": "2.0",
        "rulo": "2.0"
      },
      {
        "tag": "4_D_0020",
        "id": "41424244",
        "sifon": "6.0",
       "pisuvar": "0.0",
        "sabunluk": "6.0",
        "peçetelik": "4.0",
        "rulo": "6.0"
      },
      {
        "tag": "4_D_0023",
        "id": "41424245",
        "sifon": "3.0",
       "pisuvar": "3.0",
        "sabunluk": "4.0",
        "peçetelik": "2.0",
        "rulo": "3.0"
      },
      {
        "tag": "4_D_0167",
        "id": "41424246",
        "sifon": "1.0",
       "pisuvar": "0.0",
        "sabunluk": "1.0",
        "peçetelik": "1.0",
        "rulo": "1.0"
      },
      {
        "tag": "4_D_0169",
        "id": "41424341",
        "sifon": "1.0",
       "pisuvar": "1.0",
        "sabunluk": "1.0",
        "peçetelik": "1.0",
        "rulo": "1.0"
      },
      {
        "tag": "4_D_0006",
        "id": "41424342",
        "sifon": "6.0",
       "pisuvar": "0.0",
        "sabunluk": "6.0",
        "peçetelik": "4.0",
        "rulo": "6.0"
      },
      {
        "tag": "4_D_0009",
        "id": "41424343",
        "sifon": "3.0",
       "pisuvar": "3.0",
        "sabunluk": "4.0",
        "peçetelik": "2.0",
        "rulo": "3.0"
      },
      {
        "tag": "4_E_0022",
        "id": "41424344",
        "sifon": "4.0",
       "pisuvar": "4.0",
        "sabunluk": "5.0",
        "peçetelik": "4.0",
        "rulo": "4.0"
      },
      {
        "tag": "4_E_0026",
        "id": "41424345",
        "sifon": "8.0",
       "pisuvar": "0.0",
        "sabunluk": "8.0",
        "peçetelik": "6.0",
        "rulo": "8.0"
      },
      {
        "tag": "4_E_0014",
        "id": "41424346",
        "sifon": "1.0",
       "pisuvar": "0.0",
        "sabunluk": "1.0",
        "peçetelik": "1.0",
        "rulo": "1.0"
      },
      {
        "tag": "4_E_0016",
        "id": "41424441",
        "sifon": "1.0",
       "pisuvar": "1.0",
        "sabunluk": "1.0",
        "peçetelik": "1.0",
        "rulo": "1.0"
      },
      {
        "tag": "4_E_0031",
        "id": "41424442",
        "sifon": "1.0",
       "pisuvar": "0.0",
        "sabunluk": "1.0",
        "peçetelik": "1.0",
        "rulo": "1.0"
      },
      {
        "tag": "4_E_0033",
        "id": "41424443",
        "sifon": "1.0",
       "pisuvar": "1.0",
        "sabunluk": "1.0",
        "peçetelik": "1.0",
        "rulo": "1.0"
      },
      {
        "tag": "4_D_0063",
        "id": "41424444",
        "sifon": "2.0",
       "pisuvar": "2.0",
        "sabunluk": "4.0",
        "peçetelik": "3.0",
        "rulo": "2.0"
      },
      {
        "tag": "4_D_0066",
        "id": "41424445",
        "sifon": "4.0",
       "pisuvar": "0.0",
        "sabunluk": "4.0",
        "peçetelik": "3.0",
        "rulo": "4.0"
      },
      {
        "tag": "4_D_0098",
        "id": "41424446",
        "sifon": "2.0",
       "pisuvar": "2.0",
        "sabunluk": "4.0",
        "peçetelik": "3.0",
        "rulo": "2.0"
      },
      {
        "tag": "4_D_0101",
        "id": "41424541",
        "sifon": "4.0",
       "pisuvar": "0.0",
        "sabunluk": "4.0",
        "peçetelik": "4.0",
        "rulo": "4.0"
      },
      {
        "tag": "4_E_0063",
        "id": "41424542",
        "sifon": "4.0",
       "pisuvar": "4.0",
        "sabunluk": "5.0",
        "peçetelik": "4.0",
        "rulo": "4.0"
      },
      {
        "tag": "4_E_0065",
        "id": "41424543",
        "sifon": "4.0",
       "pisuvar": "0.0",
        "sabunluk": "4.0",
        "peçetelik": "3.0",
        "rulo": "4.0"
      },
      {
        "tag": "4_E_0056",
        "id": "41424544",
        "sifon": "1.0",
       "pisuvar": "0.0",
        "sabunluk": "1.0",
        "peçetelik": "1.0",
        "rulo": "1.0"
      },
      {
        "tag": "4_E_0058",
        "id": "41424545",
        "sifon": "1.0",
       "pisuvar": "1.0",
        "sabunluk": "1.0",
        "peçetelik": "1.0",
        "rulo": "1.0"
      },
      {
        "tag": "4_E_0081",
        "id": "41424546",
        "sifon": "1.0",
       "pisuvar": "0.0",
        "sabunluk": "1.0",
        "peçetelik": "1.0",
        "rulo": "1.0"
      },
      {
        "tag": "4_E_0083",
        "id": "41424641",
        "sifon": "1.0",
       "pisuvar": "1.0",
        "sabunluk": "1.0",
        "peçetelik": "1.0",
        "rulo": "1.0"
      },
      {
        "tag": "4_E_0097",
        "id": "41424642",
        "sifon": "1.0",
       "pisuvar": "0.0",
        "sabunluk": "1.0",
        "peçetelik": "1.0",
        "rulo": "1.0"
      },
      {
        "tag": "4_E_0099",
        "id": "41424643",
        "sifon": "1.0",
       "pisuvar": "1.0",
        "sabunluk": "1.0",
        "peçetelik": "1.0",
        "rulo": "1.0"
      },
      {
        "tag": "4_E_0160",
        "id": "41424644",
        "sifon": "3.0",
       "pisuvar": "4.0",
        "sabunluk": "3.0",
        "peçetelik": "3.0",
        "rulo": "3.0"
      },
      {
        "tag": "4_E_0161",
        "id": "41424645",
        "sifon": "5.0",
       "pisuvar": "0.0",
        "sabunluk": "3.0",
        "peçetelik": "3.0",
        "rulo": "5.0"
      },
      {
        "tag": "4_E_0116",
        "id": "41424646",
        "sifon": "4.0",
       "pisuvar": "0.0",
        "sabunluk": "3.0",
        "peçetelik": "2.0",
        "rulo": "4.0"
      },
      {
        "tag": "4_E_0120",
        "id": "41434141",
        "sifon": "2.0",
       "pisuvar": "2.0",
        "sabunluk": "2.0",
        "peçetelik": "1.0",
        "rulo": "2.0"
      },
      {
        "tag": "4_E_0126",
        "id": "41434142",
        "sifon": "1.0",
       "pisuvar": "0.0",
        "sabunluk": "1.0",
        "peçetelik": "1.0",
        "rulo": "1.0"
      },
      {
        "tag": "4_E_0128",
        "id": "41434143",
        "sifon": "1.0",
       "pisuvar": "1.0",
        "sabunluk": "1.0",
        "peçetelik": "1.0",
        "rulo": "1.0"
      },
      {
        "tag": "4_F_0031",
        "id": "41434144",
        "sifon": "4.0",
       "pisuvar": "0.0",
        "sabunluk": "4.0",
        "peçetelik": "3.0",
        "rulo": "4.0"
      },
      {
        "tag": "4_F_0032",
        "id": "41434145",
        "sifon": "2.0",
       "pisuvar": "2.0",
        "sabunluk": "3.0",
        "peçetelik": "2.0",
        "rulo": "2.0"
      },
      {
        "tag": "4_F_0017",
        "id": "41434146",
        "sifon": "4.0",
       "pisuvar": "0.0",
        "sabunluk": "4.0",
        "peçetelik": "3.0",
        "rulo": "4.0"
      },
      {
        "tag": "4_F_0018",
        "id": "41434241",
        "sifon": "3.0",
       "pisuvar": "3.0",
        "sabunluk": "3.0",
        "peçetelik": "2.0",
        "rulo": "3.0"
      },
      {
        "tag": "4_F_0011",
        "id": "41434242",
        "sifon": "3.0",
       "pisuvar": "0.0",
        "sabunluk": "3.0",
        "peçetelik": "2.0",
        "rulo": "3.0"
      },
      {
        "tag": "4_F_0012",
        "id": "41434243",
        "sifon": "3.0",
       "pisuvar": "3.0",
        "sabunluk": "4.0",
        "peçetelik": "3.0",
        "rulo": "3.0"
      },
      {
        "tag": "3_F_0002",
        "id": "41434244",
        "sifon": "4.0",
       "pisuvar": "0.0",
        "sabunluk": "4.0",
        "peçetelik": "3.0",
        "rulo": "4.0"
      },
      {
        "tag": "3_F_0005",
        "id": "41434245",
        "sifon": "3.0",
       "pisuvar": "3.0",
        "sabunluk": "3.0",
        "peçetelik": "3.0",
        "rulo": "3.0"
      },
      {
        "tag": "3_F_0014",
        "id": "41434246",
        "sifon": "4.0",
       "pisuvar": "0.0",
        "sabunluk": "4.0",
        "peçetelik": "3.0",
        "rulo": "4.0"
      },
      {
        "tag": "3_F_0017",
        "id": "41434341",
        "sifon": "3.0",
       "pisuvar": "3.0",
        "sabunluk": "4.0",
        "peçetelik": "3.0",
        "rulo": "3.0"
      },
      {
        "tag": "3_F_0030",
        "id": "41434342",
        "sifon": "3.0",
       "pisuvar": "3.0",
        "sabunluk": "4.0",
        "peçetelik": "3.0",
        "rulo": "3.0"
      },
      {
        "tag": "3_F_0033",
        "id": "41434343",
        "sifon": "4.0",
       "pisuvar": "0.0",
        "sabunluk": "4.0",
        "peçetelik": "3.0",
        "rulo": "4.0"
      },
      {
        "tag": "3_F_0047",
        "id": "41434344",
        "sifon": "3.0",
       "pisuvar": "3.0",
        "sabunluk": "3.0",
        "peçetelik": "2.0",
        "rulo": "3.0"
      },
      {
        "tag": "3_F_0049",
        "id": "41434345",
        "sifon": "4.0",
       "pisuvar": "0.0",
        "sabunluk": "3.0",
        "peçetelik": "2.0",
        "rulo": "4.0"
      },
      {
        "tag": "3_F_0061",
        "id": "41434346",
        "sifon": "4.0",
       "pisuvar": "4.0",
        "sabunluk": "4.0",
        "peçetelik": "3.0",
        "rulo": "4.0"
      },
      {
        "tag": "3_F_0062",
        "id": "41434441",
        "sifon": "4.0",
       "pisuvar": "0.0",
        "sabunluk": "4.0",
        "peçetelik": "3.0",
        "rulo": "4.0"
      },
      {
        "tag": "3_E_0203",
        "id": "41434442",
        "sifon": "3.0",
       "pisuvar": "4.0",
        "sabunluk": "3.0",
        "peçetelik": "3.0",
        "rulo": "3.0"
      },
      {
        "tag": "3_E_0204",
        "id": "41434443",
        "sifon": "5.0",
       "pisuvar": "0.0",
        "sabunluk": "3.0",
        "peçetelik": "3.0",
        "rulo": "5.0"
      },
      {
        "tag": "3_E_0151",
        "id": "41434444",
        "sifon": "4.0",
       "pisuvar": "0.0",
        "sabunluk": "4.0",
        "peçetelik": "3.0",
        "rulo": "4.0"
      },
      {
        "tag": "3_E_0152",
        "id": "41434445",
        "sifon": "4.0",
       "pisuvar": "4.0",
        "sabunluk": "4.0",
        "peçetelik": "3.0",
        "rulo": "4.0"
      },
      {
        "tag": "3_E_0127",
        "id": "41434446",
        "sifon": "4.0",
       "pisuvar": "4.0",
        "sabunluk": "5.0",
        "peçetelik": "4.0",
        "rulo": "4.0"
      },
      {
        "tag": "3_E_0131",
        "id": "41434541",
        "sifon": "4.0",
       "pisuvar": "0.0",
        "sabunluk": "4.0",
        "peçetelik": "3.0",
        "rulo": "4.0"
      },
      {
        "tag": "3_E_0115",
        "id": "41434542",
        "sifon": "1.0",
       "pisuvar": "0.0",
        "sabunluk": "1.0",
        "peçetelik": "1.0",
        "rulo": "1.0"
      },
      {
        "tag": "3_E_0117",
        "id": "41434543",
        "sifon": "1.0",
       "pisuvar": "1.0",
        "sabunluk": "1.0",
        "peçetelik": "1.0",
        "rulo": "1.0"
      },
      {
        "tag": "3_E_0086",
        "id": "41434544",
        "sifon": "1.0",
       "pisuvar": "0.0",
        "sabunluk": "1.0",
        "peçetelik": "1.0",
        "rulo": "1.0"
      },
      {
        "tag": "3_E_0088",
        "id": "41434545",
        "sifon": "1.0",
       "pisuvar": "1.0",
        "sabunluk": "1.0",
        "peçetelik": "1.0",
        "rulo": "1.0"
      },
      {
        "tag": "3_E_0090",
        "id": "41434546",
        "sifon": "5.0",
       "pisuvar": "0.0",
        "sabunluk": "5.0",
        "peçetelik": "5.0",
        "rulo": "5.0"
      },
      {
        "tag": "3_E_0094",
        "id": "41434641",
        "sifon": "5.0",
       "pisuvar": "5.0",
        "sabunluk": "5.0",
        "peçetelik": "4.0",
        "rulo": "5.0"
      },
      {
        "tag": "3_E_0037",
        "id": "41434642",
        "sifon": "5.0",
       "pisuvar": "0.0",
        "sabunluk": "5.0",
        "peçetelik": "5.0",
        "rulo": "5.0"
      },
      {
        "tag": "3_E_0041",
        "id": "41434643",
        "sifon": "5.0",
       "pisuvar": "5.0",
        "sabunluk": "5.0",
        "peçetelik": "4.0",
        "rulo": "5.0"
      },
      {
        "tag": "3_E_0042",
        "id": "41434644",
        "sifon": "1.0",
       "pisuvar": "1.0",
        "sabunluk": "1.0",
        "peçetelik": "1.0",
        "rulo": "1.0"
      },
      {
        "tag": "3_E_0044",
        "id": "41434645",
        "sifon": "1.0",
       "pisuvar": "0.0",
        "sabunluk": "1.0",
        "peçetelik": "1.0",
        "rulo": "1.0"
      },
      {
        "tag": "3_E_0021",
        "id": "41434646",
        "sifon": "8.0",
       "pisuvar": "0.0",
        "sabunluk": "8.0",
        "peçetelik": "6.0",
        "rulo": "8.0"
      },
      {
        "tag": "3_E_0025",
        "id": "41444141",
        "sifon": "4.0",
       "pisuvar": "4.0",
        "sabunluk": "5.0",
        "peçetelik": "4.0",
        "rulo": "4.0"
      },
      {
        "tag": "3_E_0007",
        "id": "41444142",
        "sifon": "1.0",
       "pisuvar": "0.0",
        "sabunluk": "1.0",
        "peçetelik": "1.0",
        "rulo": "1.0"
      },
      {
        "tag": "3_E_0009",
        "id": "41444143",
        "sifon": "1.0",
       "pisuvar": "1.0",
        "sabunluk": "1.0",
        "peçetelik": "1.0",
        "rulo": "1.0"
      },
      {
        "tag": "2_D_0006",
        "id": "41444144",
        "sifon": "3.0",
       "pisuvar": "3.0",
        "sabunluk": "4.0",
        "peçetelik": "2.0",
        "rulo": "3.0"
      },
      {
        "tag": "2_D_0009",
        "id": "41444145",
        "sifon": "6.0",
       "pisuvar": "0.0",
        "sabunluk": "6.0",
        "peçetelik": "4.0",
        "rulo": "6.0"
      },
      {
        "tag": "2_D_0040",
        "id": "41444146",
        "sifon": "3.0",
       "pisuvar": "3.0",
        "sabunluk": "4.0",
        "peçetelik": "2.0",
        "rulo": "3.0"
      },
      {
        "tag": "2_D_0037",
        "id": "41444241",
        "sifon": "6.0",
       "pisuvar": "0.0",
        "sabunluk": "6.0",
        "peçetelik": "4.0",
        "rulo": "6.0"
      },
      {
        "tag": "2_E_0016",
        "id": "41444242",
        "sifon": "4.0",
       "pisuvar": "4.0",
        "sabunluk": "5.0",
        "peçetelik": "4.0",
        "rulo": "4.0"
      },
      {
        "tag": "2_E_0012",
        "id": "41444243",
        "sifon": "8.0",
       "pisuvar": "0.0",
        "sabunluk": "8.0",
        "peçetelik": "6.0",
        "rulo": "8.0"
      },
      {
        "tag": "2_D_0060",
        "id": "41444244",
        "sifon": "2.0",
       "pisuvar": "2.0",
        "sabunluk": "4.0",
        "peçetelik": "3.0",
        "rulo": "2.0"
      },
      {
        "tag": "2_D_0064",
        "id": "41444245",
        "sifon": "4.0",
       "pisuvar": "0.0",
        "sabunluk": "4.0",
        "peçetelik": "3.0",
        "rulo": "4.0"
      },
      {
        "tag": "2_E_0039",
        "id": "41444246",
        "sifon": "4.0",
       "pisuvar": "4.0",
        "sabunluk": "4.0",
        "peçetelik": "4.0",
        "rulo": "4.0"
      },
      {
        "tag": "2_E_0035",
        "id": "41444341",
        "sifon": "4.0",
       "pisuvar": "0.0",
        "sabunluk": "4.0",
        "peçetelik": "3.0",
        "rulo": "4.0"
      },
      {
        "tag": "2_E_0144",
        "id": "41444342",
        "sifon": "3.0",
       "pisuvar": "4.0",
        "sabunluk": "3.0",
        "peçetelik": "3.0",
        "rulo": "3.0"
      },
      {
        "tag": "2_E_0145",
        "id": "41444343",
        "sifon": "5.0",
       "pisuvar": "0.0",
        "sabunluk": "3.0",
        "peçetelik": "3.0",
        "rulo": "5.0"
      },
      {
        "tag": "2_E_0078",
        "id": "41444344",
        "sifon": "2.0",
       "pisuvar": "2.0",
        "sabunluk": "2.0",
        "peçetelik": "1.0",
        "rulo": "2.0"
      },
      {
        "tag": "2_E_0077",
        "id": "41444345",
        "sifon": "4.0",
       "pisuvar": "0.0",
        "sabunluk": "3.0",
        "peçetelik": "2.0",
        "rulo": "4.0"
      },
      {
        "tag": "2_F_0003",
        "id": "41444346",
        "sifon": "3.0",
       "pisuvar": "3.0",
        "sabunluk": "4.0",
        "peçetelik": "3.0",
        "rulo": "3.0"
      },
      {
        "tag": "2_F_0006",
        "id": "41444441",
        "sifon": "3.0",
       "pisuvar": "0.0",
        "sabunluk": "3.0",
        "peçetelik": "2.0",
        "rulo": "3.0"
      },
      {
        "tag": "2_F_0017",
        "id": "41444442",
        "sifon": "3.0",
       "pisuvar": "3.0",
        "sabunluk": "4.0",
        "peçetelik": "3.0",
        "rulo": "3.0"
      },
      {
        "tag": "2_F_0016",
        "id": "41444443",
        "sifon": "3.0",
       "pisuvar": "0.0",
        "sabunluk": "3.0",
        "peçetelik": "2.0",
        "rulo": "3.0"
      },
      {
        "tag": "2_F_0030",
        "id": "41444444",
        "sifon": "2.0",
       "pisuvar": "2.0",
        "sabunluk": "3.0",
        "peçetelik": "2.0",
        "rulo": "2.0"
      },
      {
        "tag": "2_F_0029",
        "id": "41444445",
        "sifon": "4.0",
       "pisuvar": "0.0",
        "sabunluk": "4.0",
        "peçetelik": "3.0",
        "rulo": "4.0"
      },
      {
        "tag": "6_F_0052",
        "id": "41444446",
        "sifon": "8.0",
       "pisuvar": "0.0",
        "sabunluk": "4.0",
        "peçetelik": "4.0",
        "rulo": "8.0"
      },
      {
        "tag": "6_F_0650",
        "id": "6_F_0044",
        "sifon": "4.0",
       "pisuvar": "5.0",
        "sabunluk": "5.0",
        "peçetelik": "4.0",
        "rulo": "4.0"
      },
      {
        "tag": "6_F_0044",
        "id": "41444542",
        "sifon": "7.0",
       "pisuvar": "4.0",
        "sabunluk": "8.0",
        "peçetelik": "4.0",
        "rulo": "7.0"
      },
      {
        "tag": "6_F_0254",
        "id": "41444543",
        "sifon": "8.0",
       "pisuvar": "0.0",
        "sabunluk": "5.0",
        "peçetelik": "3.0",
        "rulo": "8.0"
      },
      {
        "tag": "6_F_0010",
        "id": "41444544",
        "sifon": "4.0",
       "pisuvar": "5.0",
        "sabunluk": "5.0",
        "peçetelik": "2.0",
        "rulo": "4.0"
      },
      {
        "tag": "6_F_0180",
        "id": "41444545",
        "sifon": "8.0",
       "pisuvar": "0.0",
        "sabunluk": "4.0",
        "peçetelik": "3.0",
        "rulo": "4.0"
      },
      {
        "tag": "6_F_0029",
        "id": "41444546",
        "sifon": "4.0",
       "pisuvar": "5.0",
        "sabunluk": "5.0",
        "peçetelik": "3.0",
        "rulo": "4.0"
      },
      {
        "tag": "6_F_0084",
        "id": "41444641",
        "sifon": "8.0",
       "pisuvar": "0.0",
        "sabunluk": "4.0",
        "peçetelik": "3.0",
        "rulo": "8.0"
      },
      {
        "tag": "6_F_0076",
        "id": "41444642",
        "sifon": "5.0",
       "pisuvar": "4.0",
        "sabunluk": "5.0",
        "peçetelik": "3.0",
        "rulo": "5.0"
      },
      {
        "tag": "6_F_0023",
        "id": "41444643",
        "sifon": "10.0",
       "pisuvar": "0.0",
        "sabunluk": "5.0",
        "peçetelik": "4.0",
        "rulo": "10.0"
      },
      {
        "tag": "6_F_0093",
        "id": "41444644",
        "sifon": "4.0",
       "pisuvar": "5.0",
        "sabunluk": "6.0",
        "peçetelik": "4.0",
        "rulo": "4.0"
      },
      {
        "tag": "6_F_0068",
        "id": "41444645",
        "sifon": "8.0",
       "pisuvar": "0.0",
        "sabunluk": "5.0",
        "peçetelik": "3.0",
        "rulo": "8.0"
      },
      {
        "tag": "6_F_0002",
        "id": "41444646",
        "sifon": "4.0",
       "pisuvar": "5.0",
        "sabunluk": "5.0",
        "peçetelik": "3.0",
        "rulo": "4.0"
      },
      {
        "tag": "6_F_0019",
        "id": "41454141",
        "sifon": "8.0",
       "pisuvar": "0.0",
        "sabunluk": "5.0",
        "peçetelik": "3.0",
        "rulo": "8.0"
      },
      {
        "tag": "7_F_0237",
        "id": "41454142",
        "sifon": "4.0",
       "pisuvar": "5.0",
        "sabunluk": "6.0",
        "peçetelik": "3.0",
        "rulo": "4.0"
      },
      {
        "tag": "7_F_0238",
        "id": "41454143",
        "sifon": "8.0",
       "pisuvar": "0.0",
        "sabunluk": "5.0",
        "peçetelik": "4.0",
        "rulo": "8.0"
      },
      {
        "tag": "6_F_0519",
        "id": "41454144",
        "sifon": "4.0",
       "pisuvar": "5.0",
        "sabunluk": "4.0",
        "peçetelik": "3.0",
        "rulo": "4.0"
      },
      {
        "tag": "6_F_0520",
        "id": "41454145",
        "sifon": "8.0",
       "pisuvar": "0.0",
        "sabunluk": "5.0",
        "peçetelik": "3.0",
        "rulo": "8.0"
      },
      {
        "tag": "6_F_0518",
        "id": "41454146",
        "sifon": "4.0",
       "pisuvar": "5.0",
        "sabunluk": "4.0",
        "peçetelik": "3.0",
        "rulo": "4.0"
      },
      {
        "tag": "6_F_0517",
        "id": "41454241",
        "sifon": "7.0",
       "pisuvar": "0.0",
        "sabunluk": "5.0",
        "peçetelik": "4.0",
        "rulo": "7.0"
      },
      {
        "tag": "6_F_0127",
        "id": "41454242",
        "sifon": "4.0",
       "pisuvar": "5.0",
        "sabunluk": "5.0",
        "peçetelik": "4.0",
        "rulo": "4.0"
      },
      {
        "tag": "6_F_0101",
        "id": "41454243",
        "sifon": "8.0",
       "pisuvar": "0.0",
        "sabunluk": "5.0",
        "peçetelik": "4.0",
        "rulo": "8.0"
      },
      {
        "tag": "6_H_0376",
        "id": "41454244",
        "sifon": "4.0",
       "pisuvar": "5.0",
        "sabunluk": "5.0",
        "peçetelik": "4.0",
        "rulo": "4.0"
      },
      {
        "tag": "6_H_0377",
        "id": "41454245",
        "sifon": "8.0",
       "pisuvar": "0.0",
        "sabunluk": "4.0",
        "peçetelik": "3.0",
        "rulo": "8.0"
      },
      {
        "tag": "6_H_0367",
        "id": "41454246",
        "sifon": "2.0",
       "pisuvar": "2.0",
        "sabunluk": "3.0",
        "peçetelik": "2.0",
        "rulo": "2.0"
      },
      {
        "tag": "6_H_0368",
        "id": "41454341",
        "sifon": "4.0",
       "pisuvar": "0.0",
        "sabunluk": "4.0",
        "peçetelik": "3.0",
        "rulo": "4.0"
      },
      {
        "tag": "7_F_0365",
        "id": "41454342",
        "sifon": "3.0",
       "pisuvar": "2.0",
        "sabunluk": "4.0",
        "peçetelik": "3.0",
        "rulo": "3.0"
      },
      {
        "tag": "7_F_0117",
        "id": "41454343",
        "sifon": "6.0",
       "pisuvar": "0.0",
        "sabunluk": "4.0",
        "peçetelik": "3.0",
        "rulo": "6.0"
      },
      {
        "tag": "7_F_0074",
        "id": "41454344",
        "sifon": "4.0",
       "pisuvar": "5.0",
        "sabunluk": "5.0",
        "peçetelik": "3.0",
        "rulo": "4.0"
      },
      {
        "tag": "7_F_0043",
        "id": "41454345",
        "sifon": "8.0",
       "pisuvar": "0.0",
        "sabunluk": "5.0",
        "peçetelik": "4.0",
        "rulo": "8.0"
      },
      {
        "tag": "7_F_0115",
        "id": "41454346",
        "sifon": "4.0",
       "pisuvar": "5.0",
        "sabunluk": "5.0",
        "peçetelik": "4.0",
        "rulo": "4.0"
      },
      {
        "tag": "7_F_0206",
        "id": "41454441",
        "sifon": "8.0",
       "pisuvar": "0.0",
        "sabunluk": "4.0",
        "peçetelik": "3.0",
        "rulo": "8.0"
      },
      {
        "tag": "7_F_0225",
        "id": "41454442",
        "sifon": "4.0",
       "pisuvar": "5.0",
        "sabunluk": "5.0",
        "peçetelik": "3.0",
        "rulo": "4.0"
      },
      {
        "tag": "7_F_0178",
        "id": "41454443",
        "sifon": "8.0",
       "pisuvar": "0.0",
        "sabunluk": "4.0",
        "peçetelik": "3.0",
        "rulo": "8.0"
      },
      {
        "tag": "8_F_0001",
        "id": "41454444",
        "sifon": "4.0",
       "pisuvar": "5.0",
        "sabunluk": "4.0",
        "peçetelik": "3.0",
        "rulo": "4.0"
      },
      {
        "tag": "8_F_0002",
        "id": "41454445",
        "sifon": "8.0",
       "pisuvar": "0.0",
        "sabunluk": "5.0",
        "peçetelik": "4.0",
        "rulo": "8.0"
      },
      {
        "tag": "8_F_0019",
        "id": "41454446",
        "sifon": "4.0",
       "pisuvar": "5.0",
        "sabunluk": "4.0",
        "peçetelik": "3.0",
        "rulo": "4.0"
      },
      {
        "tag": "8_F_0020",
        "id": "41454541",
        "sifon": "8.0",
       "pisuvar": "0.0",
        "sabunluk": "5.0",
        "peçetelik": "3.0",
        "rulo": "8.0"
      },
      {
        "tag": "8_F_0043",
        "id": "41454542",
        "sifon": "4.0",
       "pisuvar": "5.0",
        "sabunluk": "4.0",
        "peçetelik": "3.0",
        "rulo": "4.0"
      },
      {
        "tag": "8_F_0044",
        "id": "41454543",
        "sifon": "8.0",
       "pisuvar": "0.0",
        "sabunluk": "5.0",
        "peçetelik": "4.0",
        "rulo": "8.0"
      },
      {
        "tag": "8_F_0060",
        "id": "41454544",
        "sifon": "4.0",
       "pisuvar": "5.0",
        "sabunluk": "4.0",
        "peçetelik": "3.0",
        "rulo": "4.0"
      },
      {
        "tag": "8_F_0061",
        "id": "41454545",
        "sifon": "8.0",
       "pisuvar": "0.0",
        "sabunluk": "5.0",
        "peçetelik": "3.0",
        "rulo": "8.0"
      },
      {
        "tag": "6_F_0598",
        "id": "41454546",
        "sifon": "2.0",
       "pisuvar": "2.0",
        "sabunluk": "3.0",
        "peçetelik": "2.0",
        "rulo": "2.0"
      },
      {
        "tag": "6_F_0597",
        "id": "41454641",
        "sifon": "2.0",
       "pisuvar": "0.0",
        "sabunluk": "2.0",
        "peçetelik": "1.0",
        "rulo": "2.0"
      },
      {
        "tag": "6_F_0143",
        "id": "41454642",
        "sifon": "4.0",
       "pisuvar": "5.0",
        "sabunluk": "4.0",
        "peçetelik": "3.0",
        "rulo": "4.0"
      },
      {
        "tag": "6_F_0152",
        "id": "41454643",
        "sifon": "8.0",
       "pisuvar": "0.0",
        "sabunluk": "4.0",
        "peçetelik": "3.0",
        "rulo": "8.0"
      },
      {
        "tag": "6_E_0022",
        "id": "41454644",
        "sifon": "3.0",
       "pisuvar": "3.0",
        "sabunluk": "4.0",
        "peçetelik": "3.0",
        "rulo": "3.0"
      },
      {
        "tag": "6_E_0021",
        "id": "41454645",
        "sifon": "6.0",
       "pisuvar": "0.0",
        "sabunluk": "5.0",
        "peçetelik": "4.0",
        "rulo": "6.0"
      },
      {
        "tag": "6_E_0232",
        "id": "41454646",
        "sifon": "6.0",
       "pisuvar": "0.0",
        "sabunluk": "5.0",
        "peçetelik": "4.0",
        "rulo": "6.0"
      },
      {
        "tag": "6_E_0238",
        "id": "41464141",
        "sifon": "3.0",
       "pisuvar": "3.0",
        "sabunluk": "4.0",
        "peçetelik": "3.0",
        "rulo": "3.0"
      },
      {
        "tag": "6_E_0195",
        "id": "41464142",
        "sifon": "6.0",
       "pisuvar": "0.0",
        "sabunluk": "5.0",
        "peçetelik": "4.0",
        "rulo": "6.0"
      },
      {
        "tag": "6_E_0198",
        "id": "41464143",
        "sifon": "3.0",
       "pisuvar": "3.0",
        "sabunluk": "4.0",
        "peçetelik": "3.0",
        "rulo": "3.0"
      },
      {
        "tag": "6_E_0151",
        "id": "41464144",
        "sifon": "3.0",
       "pisuvar": "3.0",
        "sabunluk": "4.0",
        "peçetelik": "3.0",
        "rulo": "3.0"
      },
      {
        "tag": "6_E_0111",
        "id": "41464145",
        "sifon": "7.0",
       "pisuvar": "3.0",
        "sabunluk": "6.0",
        "peçetelik": "5.0",
        "rulo": "7.0"
      },
      {
        "tag": "6_E_0150",
        "id": "41464146",
        "sifon": "6.0",
       "pisuvar": "0.0",
        "sabunluk": "5.0",
        "peçetelik": "4.0",
        "rulo": "6.0"
      },
      {
        "tag": "6_E_0279",
        "id": "41464241",
        "sifon": "7.0",
       "pisuvar": "3.0",
        "sabunluk": "6.0",
        "peçetelik": "5.0",
        "rulo": "7.0"
      },
      {
        "tag": "6_E_0110",
        "id": "41464242",
        "sifon": "10.0",
       "pisuvar": "0.0",
        "sabunluk": "5.0",
        "peçetelik": "4.0",
        "rulo": "10.0"
      },
      {
        "tag": "6_E_0073",
        "id": "41464243",
        "sifon": "5.0",
       "pisuvar": "5.0",
        "sabunluk": "6.0",
        "peçetelik": "5.0",
        "rulo": "5.0"
      },
      {
        "tag": "6_E_0281",
        "id": "41464244",
        "sifon": "10.0",
       "pisuvar": "0.0",
        "sabunluk": "5.0",
        "peçetelik": "4.0",
        "rulo": "10.0"
      },
      {
        "tag": "6_E_0715",
        "id": "41464245",
        "sifon": "2.0",
       "pisuvar": "2.0",
        "sabunluk": "3.0",
        "peçetelik": "2.0",
        "rulo": "2.0"
      },
      {
        "tag": "6_E_0074",
        "id": "41464246",
        "sifon": "10.0",
       "pisuvar": "0.0",
        "sabunluk": "5.0",
        "peçetelik": "4.0",
        "rulo": "10.0"
      },
      {
        "tag": "6_E_0714",
        "id": "41464341",
        "sifon": "2.0",
       "pisuvar": "0.0",
        "sabunluk": "2.0",
        "peçetelik": "1.0",
        "rulo": "2.0"
      },
      {
        "tag": "6_E_0037",
        "id": "41464342",
        "sifon": "3.0",
       "pisuvar": "3.0",
        "sabunluk": "4.0",
        "peçetelik": "3.0",
        "rulo": "3.0"
      },
      {
        "tag": "6_E_0038",
        "id": "41464343",
        "sifon": "6.0",
       "pisuvar": "0.0",
        "sabunluk": "5.0",
        "peçetelik": "4.0",
        "rulo": "6.0"
      },
      {
        "tag": "6_E_0224",
        "id": "41464344",
        "sifon": "6.0",
       "pisuvar": "6.0",
        "sabunluk": "7.0",
        "peçetelik": "6.0",
        "rulo": "6.0"
      },
      {
        "tag": "6_E_0223",
        "id": "41464345",
        "sifon": "12.0",
       "pisuvar": "0.0",
        "sabunluk": "6.0",
        "peçetelik": "5.0",
        "rulo": "12.0"
      },
      {
        "tag": "6_E_0183",
        "id": "41464346",
        "sifon": "6.0",
       "pisuvar": "6.0",
        "sabunluk": "7.0",
        "peçetelik": "6.0",
        "rulo": "6.0"
      },
      {
        "tag": "6_E_0182",
        "id": "41464441",
        "sifon": "12.0",
       "pisuvar": "0.0",
        "sabunluk": "6.0",
        "peçetelik": "5.0",
        "rulo": "12.0"
      },
      {
        "tag": "6_E_0608",
        "id": "41464442",
        "sifon": "2.0",
       "pisuvar": "2.0",
        "sabunluk": "3.0",
        "peçetelik": "2.0",
        "rulo": "2.0"
      },
      {
        "tag": "6_E_0609",
        "id": "41464443",
        "sifon": "4.0",
       "pisuvar": "0.0",
        "sabunluk": "4.0",
        "peçetelik": "3.0",
        "rulo": "4.0"
      },
      {
        "tag": "6_E_0607",
        "id": "41464444",
        "sifon": "2.0",
       "pisuvar": "2.0",
        "sabunluk": "3.0",
        "peçetelik": "2.0",
        "rulo": "2.0"
      },
      {
        "tag": "6_E_0606",
        "id": "41464445",
        "sifon": "2.0",
       "pisuvar": "0.0",
        "sabunluk": "2.0",
        "peçetelik": "1.0",
        "rulo": "2.0"
      },
      {
        "tag": "6_D_0342",
        "id": "41464446",
        "sifon": "2.0",
       "pisuvar": "0.0",
        "sabunluk": "2.0",
        "peçetelik": "1.0",
        "rulo": "2.0"
      },
      {
        "tag": "6_D_0341",
        "id": "41464541",
        "sifon": "2.0",
       "pisuvar": "2.0",
        "sabunluk": "3.0",
        "peçetelik": "2.0",
        "rulo": "2.0"
      },
      {
        "tag": "6_D_0343",
        "id": "41464542",
        "sifon": "2.0",
       "pisuvar": "0.0",
        "sabunluk": "2.0",
        "peçetelik": "1.0",
        "rulo": "2.0"
      },
      {
        "tag": "6_D_0344",
        "id": "41464543",
        "sifon": "2.0",
       "pisuvar": "2.0",
        "sabunluk": "3.0",
        "peçetelik": "2.0",
        "rulo": "2.0"
      },
      {
        "tag": "7_D_0324",
        "id": "41464544",
        "sifon": "8.0",
       "pisuvar": "0.0",
        "sabunluk": "4.0",
        "peçetelik": "3.0",
        "rulo": "8.0"
      },
      {
        "tag": "7_D_0325",
        "id": "41464545",
        "sifon": "4.0",
       "pisuvar": "5.0",
        "sabunluk": "5.0",
        "peçetelik": "4.0",
        "rulo": "4.0"
      },
      {
        "tag": "7_D_0318",
        "id": "41464546",
        "sifon": "8.0",
       "pisuvar": "0.0",
        "sabunluk": "4.0",
        "peçetelik": "3.0",
        "rulo": "8.0"
      },
      {
        "tag": "7_D_0319",
        "id": "41464641",
        "sifon": "4.0",
       "pisuvar": "5.0",
        "sabunluk": "5.0",
        "peçetelik": "4.0",
        "rulo": "4.0"
      },
      {
        "tag": "7_D_0320",
        "id": "41464642",
        "sifon": "8.0",
       "pisuvar": "0.0",
        "sabunluk": "4.0",
        "peçetelik": "3.0",
        "rulo": "8.0"
      },
      {
        "tag": "7_D_0321",
        "id": "41464643",
        "sifon": "4.0",
       "pisuvar": "5.0",
        "sabunluk": "5.0",
        "peçetelik": "4.0",
        "rulo": "4.0"
      },
      {
        "tag": "7_D_0322",
        "id": "41464644",
        "sifon": "8.0",
       "pisuvar": "0.0",
        "sabunluk": "4.0",
        "peçetelik": "3.0",
        "rulo": "8.0"
      },
      {
        "tag": "7_D_0323",
        "id": "41464645",
        "sifon": "0.0",
       "pisuvar": "5.0",
        "sabunluk": "5.0",
        "peçetelik": "4.0",
        "rulo": "4.0"
      },
      {
        "tag": "8_D_0428",
        "id": "41464646",
        "sifon": "3.0",
       "pisuvar": "3.0",
        "sabunluk": "3.0",
        "peçetelik": "2.0",
        "rulo": "3.0"
      },
      {
        "tag": "8_D_0427",
        "id": "42414141",
        "sifon": "6.0",
       "pisuvar": "0.0",
        "sabunluk": "4.0",
        "peçetelik": "3.0",
        "rulo": "6.0"
      },
      {
        "tag": "8_D_0430",
        "id": "42414142",
        "sifon": "8.0",
       "pisuvar": "0.0",
        "sabunluk": "4.0",
        "peçetelik": "3.0",
        "rulo": "8.0"
      },
      {
        "tag": "8_D_0429",
        "id": "42414143",
        "sifon": "4.0",
       "pisuvar": "5.0",
        "sabunluk": "5.0",
        "peçetelik": "4.0",
        "rulo": "4.0"
      },
      {
        "tag": "8_D_0438",
        "id": "42414144",
        "sifon": "8.0",
       "pisuvar": "0.0",
        "sabunluk": "4.0",
        "peçetelik": "3.0",
        "rulo": "8.0"
      },
      {
        "tag": "8_D_0437",
        "id": "42414145",
        "sifon": "4.0",
       "pisuvar": "5.0",
        "sabunluk": "5.0",
        "peçetelik": "4.0",
        "rulo": "4.0"
      },
      {
        "tag": "8_D_0434",
        "id": "42414146",
        "sifon": "8.0",
       "pisuvar": "0.0",
        "sabunluk": "4.0",
        "peçetelik": "3.0",
        "rulo": "8.0"
      },
      {
        "tag": "8_D_0433",
        "id": "42414241",
        "sifon": "4.0",
       "pisuvar": "5.0",
        "sabunluk": "5.0",
        "peçetelik": "4.0",
        "rulo": "4.0"
      },
      {
        "tag": "8_D_0435",
        "id": "42414242",
        "sifon": "12.0",
       "pisuvar": "5.0",
        "sabunluk": "10.0",
        "peçetelik": "8.0",
        "rulo": "12.0"
      },
      {
        "tag": "8_D_0432",
        "id": "42414243",
        "sifon": "4.0",
       "pisuvar": "5.0",
        "sabunluk": "5.0",
        "peçetelik": "4.0",
        "rulo": "4.0"
      },
      {
        "tag": "8_D_0436",
        "id": "42414244",
        "sifon": "16.0",
       "pisuvar": "0.0",
        "sabunluk": "11.0",
        "peçetelik": "9.0",
        "rulo": "16.0"
      },
      {
        "tag": "8_D_0431",
        "id": "42414245",
        "sifon": "8.0",
       "pisuvar": "0.0",
        "sabunluk": "4.0",
        "peçetelik": "3.0",
        "rulo": "8.0"
      },
      {
        "tag": "8_D_0425",
        "id": "42414246",
        "sifon": "3.0",
       "pisuvar": "4.0",
        "sabunluk": "5.0",
        "peçetelik": "4.0",
        "rulo": "3.0"
      },
      {
        "tag": "8_D_0426",
        "id": "42414341",
        "sifon": "6.0",
       "pisuvar": "0.0",
        "sabunluk": "4.0",
        "peçetelik": "3.0",
        "rulo": "6.0"
      }
    ]
  }
  